sknlp/__init__.py
sknlp/activations/__init__.py
sknlp/callbacks/__init__.py
sknlp/callbacks/tagging_fscore_metric.py
sknlp/data/__init__.py
sknlp/data/bert_mixin.py
sknlp/data/classification_dataset.py
sknlp/data/generation_dataset.py
sknlp/data/nlp_dataset.py
sknlp/data/retrieval_dataset.py
sknlp/data/tagging_dataset.py
sknlp/data/tokenizer.py
sknlp/data/utils.py
sknlp/layers/__init__.py
sknlp/layers/attention.py
sknlp/layers/bert_attention_mask.py
sknlp/layers/bert_layer.py
sknlp/layers/bert_lm.py
sknlp/layers/bert_seq2seq.py
sknlp/layers/bilstm.py
sknlp/layers/crf_layer.py
sknlp/layers/dilated_convolution.py
sknlp/layers/global_pointer.py
sknlp/layers/mlp.py
sknlp/layers/preprocessing_layer.py
sknlp/layers/sinusoidal_position_embedding.py
sknlp/layers/transformer_encoder_block.py
sknlp/layers/utils/__init__.py
sknlp/layers/utils/bert_converter.py
sknlp/losses/__init__.py
sknlp/losses/losses.py
sknlp/metrics/__init__.py
sknlp/metrics/accuracy.py
sknlp/metrics/precision_recall_f1.py
sknlp/metrics/utils.py
sknlp/module/__init__.py
sknlp/module/base_model.py
sknlp/module/classifiers/__init__.py
sknlp/module/classifiers/bert_classifier.py
sknlp/module/classifiers/cnn_classifier.py
sknlp/module/classifiers/deep_classifier.py
sknlp/module/classifiers/rcnn_classifier.py
sknlp/module/classifiers/rnn_classifier.py
sknlp/module/generators/__init__.py
sknlp/module/generators/bert_generator.py
sknlp/module/generators/deep_generator.py
sknlp/module/parameter_search.py
sknlp/module/retrievers/__init__.py
sknlp/module/retrievers/bert_retriever.py
sknlp/module/retrievers/deep_retriever.py
sknlp/module/retrievers/rnn_retriever.py
sknlp/module/supervised_model.py
sknlp/module/taggers/__init__.py
sknlp/module/taggers/bert_rnn_tagger.py
sknlp/module/taggers/bert_tagger.py
sknlp/module/taggers/cnn_tagger.py
sknlp/module/taggers/deep_tagger.py
sknlp/module/taggers/rnn_tagger.py
sknlp/module/text2vec/__init__.py
sknlp/module/text2vec/bert2vec.py
sknlp/module/text2vec/bert_config.py
sknlp-0.5.0.dist-info/WHEEL
sknlp-0.5.0.dist-info/METADATA
sknlp-0.5.0.dist-info/RECORD
