Metadata-Version: 2.1
Name: sknlp
Version: 0.5.0
Summary: 
License: MIT
Author: nanaya
Author-email: nanaya100@gmail.com
Requires-Python: >=3.7.5,<3.10
Classifier: License :: OSI Approved :: MIT License
Classifier: Programming Language :: Python :: 3
Classifier: Programming Language :: Python :: 3.8
Classifier: Programming Language :: Python :: 3.9
Requires-Dist: igraph (>=0.9.8,<0.10.0)
Requires-Dist: jieba (>=0.42.1,<0.43.0)
Requires-Dist: keras-tuner (>=1.0.2,<2.0.0)
Requires-Dist: pandas (==1.3.1)
Requires-Dist: scikit-learn (==1.0)
Requires-Dist: tabulate (==0.8.9)
Requires-Dist: tensorflow (==2.7.1)
Requires-Dist: tensorflow-addons (==0.15.0)
Requires-Dist: tensorflow-text (==2.7.3)
